mltoolhub/__init__.py
mltoolhub/basics.py
mltoolhub/prologger.py
mltoolhub/modelling/__init__.py
mltoolhub/modelling/tabular/__init__.py
mltoolhub/preprocessing/__init__.py
mltoolhub/preprocessing/tabular/__init__.py
mltoolhub/preprocessing/tabular/imputers.py
mltoolhub-0.0.19.dist-info/licenses/LICENSE
mltoolhub-0.0.19.dist-info/METADATA
mltoolhub-0.0.19.dist-info/WHEEL
mltoolhub-0.0.19.dist-info/top_level.txt
mltoolhub-0.0.19.dist-info/RECORD
