Metadata-Version: 2.4
Name: mltoolhub
Version: 0.0.19
Summary: A lightweight toolkit for faster model building.
Author-email: Kishan Mishra <kishanmldev@gmail.com>
License-Expression: MIT
Classifier: Programming Language :: Python :: 3
Classifier: Operating System :: OS Independent
Requires-Python: >=3.9
License-File: LICENSE
Requires-Dist: numpy
Requires-Dist: pandas
Requires-Dist: matplotlib
Requires-Dist: seaborn
Requires-Dist: lightgbm
Requires-Dist: tqdm
Dynamic: license-file
